ibm_watsonxdata_dl_retrieval_mcp_server/__init__.py
ibm_watsonxdata_dl_retrieval_mcp_server/__main__.py
ibm_watsonxdata_dl_retrieval_mcp_server/document_library_api.py
ibm_watsonxdata_dl_retrieval_mcp_server/retrival_service_api.py
ibm_watsonxdata_dl_retrieval_mcp_server/server.py
ibm_watsonxdata_dl_retrieval_mcp_server/utils.py
ibm_watsonxdata_dl_retrieval_mcp_server-0.2.9.dist-info/METADATA
ibm_watsonxdata_dl_retrieval_mcp_server-0.2.9.dist-info/WHEEL
ibm_watsonxdata_dl_retrieval_mcp_server-0.2.9.dist-info/entry_points.txt
ibm_watsonxdata_dl_retrieval_mcp_server-0.2.9.dist-info/licenses/LICENSE
ibm_watsonxdata_dl_retrieval_mcp_server-0.2.9.dist-info/RECORD
