Metadata-Version: 2.4
Name: ibm-watsonxdata-dl-retrieval-mcp-server
Version: 0.2.9
Summary: An IBM watsonx.data mcp server that seamlessly connects AI agents with document libraries
Project-URL: Repository, https://github.com/IBM/ibm-watsonxdata-dl-retrieval-mcp-server.git
Project-URL: Bug Tracker, https://github.com/IBM/ibm-watsonxdata-dl-retrieval-mcp-server/issues
Author: IBM watsonx.data
License: Apache-2.0
License-File: LICENSE
Classifier: Development Status :: 5 - Production/Stable
Classifier: License :: OSI Approved :: Apache Software License
Classifier: Operating System :: MacOS :: MacOS X
Classifier: Operating System :: Microsoft :: Windows
Classifier: Operating System :: POSIX :: Linux
Classifier: Programming Language :: Python
Classifier: Programming Language :: Python :: 3
Classifier: Programming Language :: Python :: 3.11
Classifier: Programming Language :: Python :: 3.12
Classifier: Topic :: Software Development :: Libraries :: Python Modules
Requires-Python: >=3.11
Requires-Dist: fastmcp==2.13.0
Requires-Dist: mcp[cli,sse]>=1.17.0
Requires-Dist: requests==2.32.4
Provides-Extra: dev
Requires-Dist: build>=1.2.2.post1; extra == 'dev'
Requires-Dist: twine>=6.1.0; extra == 'dev'
